{
  "subscription_plans": [
    {
      "speed": "10",
      "key": "primesubscription",
      "month3": "118",
      "month6": "204",
      "month12": "314"
    },
    {
      "speed": "20",
      "key": "elitesubscription",
      "month3": "225",
      "month6": "390",
      "month12": "600"
    },
    {
      "speed": "30",
      "key": "ultrapro",
      "month3": "332",
      "month6": "576",
      "month12": "886"
    },
    {
      "speed": "40",
      "key": "40xsubscribe",
      "month3": "386",
      "month6": "669",
      "month12": "1029"
    },
    {
      "speed": "50",
      "key": "50xsubscribe",
      "month3": "429",
      "month6": "743",
      "month12": "1143"
    },
    {
      "speed": "60",
      "key": "60xsubscribe",
      "month3": "546",
      "month6": "947",
      "month12": "1457"
    }
  ],
  "1Month": {
    "name": "1 month",
    "plantext": "Longer duration is cheaper",
    "plans": [
      {
        "speed": "10",
        "key": "5xspeed1month",
        "month3": "612",
        "month6": "1060",
        "month12": "1632"
      },
      {
        "speed": "20",
        "key": "10xspeed1month",
        "month3": "612",
        "month6": "1060",
        "month12": "1632"
      },
      {
        "speed": "30",
        "key": "30xspeed1month",
        "month3": "612",
        "month6": "1060",
        "month12": "1632"
      },
      {
        "speed": "40",
        "key": "40xspeed1month",
        "month3": "612",
        "month6": "1060",
        "month12": "1632"
      },
      {
        "speed": "50",
        "key": "50xspeed1month",
        "month3": "612",
        "month6": "1060",
        "month12": "1632"
      }
    ]
  },
  "3Month": {
    "name": "3 month",
    "plantext": "25% discount",
    "plans": [
      {
        "speed": "10",
        "key": "5xspeed3month",
        "month6": "1060",
        "month12": "1632"
      },
      {
        "speed": "20",
        "key": "10xspeed3month",
        "month6": "1060",
        "month12": "1632"
      },
      {
        "speed": "30",
        "key": "$496",
        "month6": "1060",
        "month12": "1632"
      },
      {
        "speed": "40",
        "key": "$576",
        "month6": "1060",
        "month12": "1632"
      },
      {
        "speed": "50",
        "key": "$640",
        "month6": "1060",
        "month12": "1632"
      }
    ]
  },
  "6Month": {
    "name": "6 month",
    "plantext": "33% discount",
    "plans": [
      {
        "speed": "10",
        "key": "5xspeed6month",
        "month12": "1632"
      },
      {
        "speed": "20",
        "key": "$672",
        "month12": "1632"
      },
      {
        "speed": "30",
        "key": "$992",
        "month12": "1632"
      },
      {
        "speed": "40",
        "key": "$1152",
        "month12": "1632"
      },
      {
        "speed": "50",
        "key": "$1280",
        "month12": "1632"
      }
    ]
  },
  "12Month": {
    "name": "12 month",
    "plantext": "50% discount",
    "plans": [
      {
        "speed": "10",
        "key": "$704"
      },
      {
        "speed": "20",
        "key": "$1344"
      },
      {
        "speed": "30",
        "key": "$1984"
      },
      {
        "speed": "40",
        "key": "$2304"
      },
      {
        "speed": "50",
        "key": "$2560"
      }
    ]
  }
}
